ATTACK_THE_ENEMY_RPG/attack_the_enemy_rpg.py
ATTACK_THE_ENEMY_RPG-1.dist-info/LICENSE
ATTACK_THE_ENEMY_RPG-1.dist-info/METADATA
ATTACK_THE_ENEMY_RPG-1.dist-info/WHEEL
ATTACK_THE_ENEMY_RPG-1.dist-info/entry_points.txt
ATTACK_THE_ENEMY_RPG-1.dist-info/top_level.txt
ATTACK_THE_ENEMY_RPG-1.dist-info/RECORD
